stram/__init__.py
stram/domain/__init__.py
stram/domain/style_product.py
stram/domain/methods/__init__.py
stram/domain/methods/base_method.py
stram/domain/methods/gatys_method.py
stram/domain/methods/reinhard_method.py
stram/domain/methods/yijun_method.py
stram/domain/toolsets/__init__.py
stram/domain/toolsets/gatys_toolset.py
stram/domain/toolsets/general_toolset.py
stram/domain/toolsets/reinhard_toolset.py
stram/domain/toolsets/yijun_toolset.py
stram/services/__init__.py
stram/services/commander.py
stram/services/executor.py
stram/services/method_factory.py
stram/utils/__init__.py
stram/utils/exceptions.py
stram/utils/export.py
stram/utils/hashing.py
stram/utils/image_processing.py
stram/utils/json_processing.py
stram/utils/worklog.py
stram-1.0.2.dist-info/METADATA
stram-1.0.2.dist-info/WHEEL
stram-1.0.2.dist-info/top_level.txt
stram-1.0.2.dist-info/RECORD
