Metadata-Version: 2.1
Name: stram
Version: 1.0.2
Summary: Style TRAnsfer Machine - a package for performing image style transfer using machine learning methods
Home-page: https://gitlab.com/forgeai/style2pic.git
Author: emilutz
Author-email: emil.barbutza@gmail.com
License: UNKNOWN
Platform: UNKNOWN
Classifier: Programming Language :: Python :: 3
Classifier: License :: OSI Approved :: MIT License
Classifier: Operating System :: OS Independent
Requires-Python: >=3.7, <3.8
Requires-Dist: bunch
Requires-Dist: numpy
Requires-Dist: opencv-python
Requires-Dist: pydot
Requires-Dist: scipy
Requires-Dist: static-variables
Requires-Dist: python-decouple
Requires-Dist: tensorflow (>=2.7)
Requires-Dist: tensorflow-hub
Requires-Dist: tensorflow-io
Requires-Dist: tqdm
